README.md
setup.py
journeemondiale/__init__.py
python_journee_mondiale.egg-info/PKG-INFO
python_journee_mondiale.egg-info/SOURCES.txt
python_journee_mondiale.egg-info/dependency_links.txt
python_journee_mondiale.egg-info/not-zip-safe
python_journee_mondiale.egg-info/requires.txt
python_journee_mondiale.egg-info/top_level.txt