Metadata-Version: 1.0
Name: python-journee-mondiale
Version: 0.0.1
Summary: Very useful Python API To get World Days
Home-page: https://github.com/remaudcorentin-dev/python-journee-mondiale
Author: Corentin Remaud
Author-email: remaudcorentin.dev@gmail.com
License: MIT
Platform: UNKNOWN
